{
  "name": "Crucible Guard",
  "color": "#85d1bd",
  "models": {
    "casters": {
      "gearhart1": {
        "name": "Gearhart1 (Marshal General Baldwin Gearhart)",
        "entries": {
          "caster": {
            "gearhart1": {
              "name": "Gearhart",
              "type": "wardude",
              "focus": 6,
              "base": "small",
              "img": [],
              "damage": {
                "n": 17
              }
            }
          },
          "solo": {
            "cloggs": {
              "name": "Mr Cloggs",
              "type": "solo",
              "base": "small",
              "img": [],
              "damage": {
                "n": 5
              }
            }
          }
        }
      },
      "locke1": {
        "name": "Locke1 (Aurum Lucanum Athanor Locke)",
        "type": "wardude",
        "focus": 7,
        "base": "medium",
        "img": [],
        "damage": {
          "n": 18
        }
      },
      "lukas1": {
        "name": "Lukas1 (Aurum Legate Lukas di Morray)",
        "type": "wardude",
        "focus": 5,
        "base": "small",
        "img": [],
        "damage": {
          "n": 18
        }
      },
      "mackay1": {
        "name": "Mackay1 (Captain Eira Mackay)",
        "type": "wardude",
        "focus": 6,
        "base": "huge",
        "img": [],
        "damage": {
          "n": 36
        }
      },
      "syvestro1": {
        "name": "Syvestro1 (Aurum Adeptus Syvestro)",
        "type": "wardude",
        "focus": 7,
        "base": "small",
        "img": [],
        "damage": {
          "n": 15
        }
      }
    },
    "jacks": {
      "liberator": {
        "name": "Liberator",
        "type": "jack",
        "base": "medium",
        "img": [],
        "damage": {
          "type": "jack",
          "1": [ null, null,  "b",  "b",  "l", null ],
          "2": [ null,  "b",  "b",  "l",  "l",  "m" ],
          "3": [ null,  "b",  "b",  "a",  "m",  "m" ],
          "4": [ null,  "b",  "b",  "a",  "c",  "c" ],
          "5": [ null,  "b",  "b",  "r",  "r",  "c" ],
          "6": [ null, null,  "b",  "b",  "r", null ]
        }
      },
      "retaliator": {
        "name": "Retaliator",
        "type": "jack",
        "base": "medium",
        "img": [],
        "damage": {
          "type": "jack",
          "1": [ null, null,  "b",  "b",  "l", null ],
          "2": [ null,  "b",  "b",  "l",  "l",  "m" ],
          "3": [ null,  "b",  "b",  "b",  "m",  "m" ],
          "4": [ null,  "b",  "b",  "b",  "c",  "c" ],
          "5": [ null,  "b",  "b",  "r",  "r",  "c" ],
          "6": [ null, null,  "b",  "b",  "r", null ]
        }
      },
      "vanguard": {
        "name": "Vanguard",
        "type": "jack",
        "base": "medium",
        "img": [],
        "damage": {
          "type": "jack",
          "1": [ null, null,  "b",  "b",  "l", null ],
          "2": [ null,  "b",  "b",  "l",  "l",  "m" ],
          "3": [ null,  "b",  "b",  "b",  "m",  "m" ],
          "4": [ null,  "b",  "b",  "b",  "c",  "c" ],
          "5": [ null,  "b",  "b",  "r",  "r",  "c" ],
          "6": [ null, null,  "b",  "b",  "r", null ]
        }
      },
      "suppressor": {
        "name": "Suppressor",
        "type": "jack",
        "base": "large",
        "img": [],
        "damage": {
          "type": "jack",
          "1": [ null, "b",  "b",  "b",  "l", null ],
          "2": [ null, "b",  "b",  "l",  "l",  "m" ],
          "3": [ "b",  "b",  "b",  "b",  "m",  "m" ],
          "4": [ "b",  "b",  "b",  "b",  "c",  "c" ],
          "5": [ null, "b",  "b",  "r",  "r",  "c" ],
          "6": [ null, "b",  "b",  "b",  "r", null ]
        }
      },
      "toro": {
        "name": "Toro",
        "type": "jack",
        "base": "large",
        "img": [],
        "damage": {
          "type": "jack",
          "1": [ null,  "b",  "b",  "b",  "l", null ],
          "2": [ null,  "b",  "b",  "l",  "l",  "m" ],
          "3": [  "b",  "b",  "b",  "b",  "m",  "m" ],
          "4": [  "b",  "b",  "b",  "b",  "c",  "c" ],
          "5": [ null,  "b",  "b",  "r",  "r",  "c" ],
          "6": [ null,  "b",  "b",  "b",  "r", null ]
        }
      },
      "vindicator": {
        "name": "Vindicator",
        "type": "jack",
        "base": "large",
        "img": [],
        "damage": {
          "type": "jack",
          "1": [ null, "b",  "b",  "b",  "l", null ],
          "2": [ null, "b",  "b",  "l",  "l",  "m" ],
          "3": [ "b",  "b",  "b",  "b",  "m",  "m" ],
          "4": [ "b",  "b",  "b",  "b",  "c",  "c" ],
          "5": [ null, "b",  "b",  "r",  "r",  "c" ],
          "6": [ null, "b",  "b",  "b",  "r", null ]
        }
      },
      "vulcan": {
        "name": "Vulcan",
        "type": "jack",
        "base": "huge",
        "img": [],
        "damage": {
          "type": "colossal",
          "L1": [ null, null,  "b",  "b",  "l",  "l" ],
          "L2": [ null, null,  "b",  "b",  "l",  "c" ],
          "L3": [ null, null,  "b",  "l",  "c",  "m" ],
          "L4": [ null,  "b",  "b",  "l",  "c",  "m" ],
          "L5": [  "b",  "b",  "s",  "s",  "c",  "m" ],
          "L6": [  "b",  "b",  "s",  "c",  "c",  "m" ],
          "R1": [  "b",  "b",  "s",  "c",  "c",  "m" ],
          "R2": [  "b",  "b",  "s",  "s",  "c",  "m" ],
          "R3": [ null,  "b",  "b",  "r",  "c",  "m" ],
          "R4": [ null, null,  "b",  "r",  "c",  "m" ],
          "R5": [ null, null,  "b",  "b",  "r",  "c" ],
          "R6": [ null, null,  "b",  "b",  "r",  "r" ]
        }
      }
    },
    "units": {
      "combat alchemists": {
        "name": "Combat Alchemists",
        "entries": {
          "unit": {
            "grunt": {
              "name": "Leader and Grunts",
              "ranges": [1, 3],
              "type": "warrior",
              "base": "small",
              "img": []
            }
          }
        }
      },
      "assault troopers": {
        "name": "Crucible Guard Assault Troopers",
        "entries": {
          "unit": {
            "grunt": {
              "name": "Leader and Grunts",
              "ranges": [1, 3, 5],
              "type": "warrior",
              "base": "medium",
              "img": [],
              "damage": {
                "n": 5
              }
            }
          }
        }
      },
      "Infantry": {
        "name": "Crucible Guard Infantry",
        "entries": {
          "unit": {
            "grunt": {
              "name": "Infantry",
              "ranges": [1, 6, 10],
              "type": "warrior",
              "base": "small",
              "img": []
            }
          },
          "ua": {
            "officer": {
              "name": "Officer",
              "type": "warrior",
              "base": "small",
              "img": [],
              "damage": {
                "n": 5
              }
            },
            "standard": {
              "name": "Standard Bearer",
              "type": "warrior",
              "base": "small",
              "img": []
            }
          }
        }
      },
      "rocketmen": {
        "name": "Crucible Guard Rocketmen",
        "entries": {
          "unit": {
            "grunt": {
              "name": "Leader and Grunts",
              "ranges": [1, 6, 10],
              "type": "warrior",
              "base": "small",
              "img": []
            }
          },
          "ua": {
            "captain": {
              "name": "Rocketman Captain",
              "type": "warrior",
              "base": "small",
              "img": [],
              "damage": {
                "n": 5
              }
            },
            "gunner": {
              "name": "Rocketman Gunner",
              "type": "warrior",
              "base": "small",
              "img": []
            }
          }
        }
      },
      "storm troopers": {
        "name": "Crucible Guard Storm Troopers",
        "entries": {
          "unit": {
            "grunt": {
              "name": "Leader and Grunts",
              "ranges": [1, 3, 5],
              "type": "warrior",
              "base": "medium",
              "img": [],
              "damage": {
                "n": 5
              }
            }
          }
        }
      },
      "dragon's breath": {
        "name": "Dragon's Breath Rocket",
        "entries": {
          "unit": {
            "grunt": {
              "name": "Crew",
              "type": "warrior",
              "base": "small",
              "img": []
            },
            "gunner": {
              "name": "Gunner",
              "type": "warrior",
              "base": "large",
              "img": []
            }
          }
        }
      }
    },
    "solos": {
      "alyce (little)": {
        "name": "Aurum Ominus Alyce Marc",
        "type": "warrior",
        "base": "small",
        "img": [],
        "damage": {
          "n": 5
        }
      },
      "alyce (big)": {
        "name": "Aurum Ominus Alyce Marc",
        "type": "warrior",
        "base": "large",
        "img": [],
        "damage": {
          "n": 8
        }
      },
      "mechanik": {
        "name": "Crucible Guard Mechanik",
        "type": "warrior",
        "base": "small",
        "img": []
      },
      "mosby": {
        "name": "Doctor Alejandro Mosby",
        "type": "solo",
        "base": "small",
        "img": [],
        "damage": {
          "n": 5
        }
      },
      "prospero": {
        "name": "Prospero",
        "type": "wardude",
        "focus": 4,
        "base": "medium",
        "img": [],
        "damage": {
          "n": 8
        }
      },
      "rocketman ace": {
        "name": "Rocketman Ace",
        "type": "solo",
        "base": "small",
        "img": [],
        "damage": {
          "n": 5
        }
      },
      "trancer": {
        "name": "Trancer",
        "type": "solo",
        "base": "small",
        "img": [],
        "damage": {
          "n": 5
        }
      }
    },
    "battle_engines": {
      "railess interceptor": {
        "name": "Railless Interceptor",
        "type": "be",
        "base": "huge",
        "img": [],
        "damage": {
          "n": 36
        }
      }
    }
  }
}
